teams_webhook/__init__.py
teams_webhook/examples.py
teams_webhook/teams_webhook.py
teams_webhook/test_teams_webhook.py
teams_webhook-1.0.0.dist-info/licenses/LICENSE
teams_webhook-1.0.0.dist-info/METADATA
teams_webhook-1.0.0.dist-info/WHEEL
teams_webhook-1.0.0.dist-info/top_level.txt
teams_webhook-1.0.0.dist-info/RECORD
