Metadata-Version: 2.4
Name: teams-webhook
Version: 1.0.0
Summary: A simple Python package to send messages to Microsoft Teams using webhooks
Home-page: https://github.com/pandiyarajk/teams-webhook
Author: Pandiyaraj Karuppasamy
Author-email: Pandiyaraj Karuppasamy <pandiyarajk@live.com>
License-Expression: MIT
Project-URL: Homepage, https://github.com/pandiyarajk/teams-webhook
Project-URL: Documentation, https://github.com/pandiyarajk/teams-webhook#readme
Project-URL: Repository, https://github.com/pandiyarajk/teams-webhook
Project-URL: Bug Reports, https://github.com/pandiyarajk/teams-webhook/issues
Keywords: microsoft,teams,webhook,notification,messaging
Classifier: Development Status :: 4 - Beta
Classifier: Intended Audience :: Developers
Classifier: Operating System :: OS Independent
Classifier: Programming Language :: Python :: 3
Classifier: Programming Language :: Python :: 3.7
Classifier: Programming Language :: Python :: 3.8
Classifier: Programming Language :: Python :: 3.9
Classifier: Programming Language :: Python :: 3.10
Classifier: Programming Language :: Python :: 3.11
Classifier: Programming Language :: Python :: 3.12
Classifier: Topic :: Communications :: Chat
Classifier: Topic :: Software Development :: Libraries :: Python Modules
Requires-Python: >=3.7
License-File: LICENSE
Requires-Dist: requests>=2.25.0
Provides-Extra: dev
Requires-Dist: pytest>=6.0; extra == "dev"
Requires-Dist: pytest-cov>=2.0; extra == "dev"
Requires-Dist: black>=21.0; extra == "dev"
Requires-Dist: flake8>=3.8; extra == "dev"
Provides-Extra: test
Requires-Dist: pytest>=6.0; extra == "test"
Requires-Dist: pytest-cov>=2.0; extra == "test"
Dynamic: author
Dynamic: home-page
Dynamic: license-file
Dynamic: requires-python
